graph_db_interface/__init__.py
graph_db_interface/exceptions.py
graph_db_interface/graph_db.py
graph_db_interface/kafka/kafka_manager.py
graph_db_interface/queries/named_graph.py
graph_db_interface/queries/ontology_helpers.py
graph_db_interface/queries/rdf4j/graph_store.py
graph_db_interface/queries/triple_multi.py
graph_db_interface/queries/triple_single.py
graph_db_interface/sparql_query.py
graph_db_interface/utils/__init__.py
graph_db_interface/utils/graph_db_credentials.py
graph_db_interface/utils/pretty_print.py
graph_db_interface/utils/processing.py
graph_db_interface/utils/utils.py
graph_db_interface-1.1.0.dist-info/METADATA
graph_db_interface-1.1.0.dist-info/WHEEL
graph_db_interface-1.1.0.dist-info/licenses/LICENSE
graph_db_interface-1.1.0.dist-info/RECORD
