Metadata-Version: 2.4
Name: graph-db-interface
Version: 1.1.0
Summary: A simple interface to interact with a GraphDB instance
License-File: LICENSE
Author: Jan-Felix Klein
Author-email: janfelixklein@ooglemail.com
Requires-Python: >=3.11,<4.0
Classifier: Programming Language :: Python :: 3
Classifier: Programming Language :: Python :: 3.11
Classifier: Programming Language :: Python :: 3.12
Classifier: Programming Language :: Python :: 3.13
Classifier: Programming Language :: Python :: 3.14
Requires-Dist: python-snappy (>=0.7.3,<0.8.0)
Requires-Dist: rdflib (==7.1.3)
Requires-Dist: requests (>=2.32.3,<3.0.0)
